llama_index/readers/openalex/__init__.py
llama_index/readers/openalex/base.py
llama_index_readers_openalex-0.4.1.dist-info/METADATA
llama_index_readers_openalex-0.4.1.dist-info/WHEEL
llama_index_readers_openalex-0.4.1.dist-info/licenses/LICENSE
llama_index_readers_openalex-0.4.1.dist-info/RECORD
