Metadata-Version: 2.4
Name: llama-index-readers-openalex
Version: 0.4.1
Summary: llama-index readers openalex integration
Author-email: Your Name <you@example.com>
Maintainer: shauryr
License-Expression: MIT
License-File: LICENSE
Keywords: academic papers,open access,openalex,scientific papers
Requires-Python: <4.0,>=3.9
Requires-Dist: llama-index-core<0.15,>=0.13.0
